distance_calculation/__init__.py
distance_calculation/distance_calculation.py
dist_calculating-0.0.1.dist-info/LICENSE
dist_calculating-0.0.1.dist-info/METADATA
dist_calculating-0.0.1.dist-info/WHEEL
dist_calculating-0.0.1.dist-info/top_level.txt
dist_calculating-0.0.1.dist-info/RECORD
