Metadata-Version: 2.1
Name: dist-calculating
Version: 0.0.1
Summary: A package that can calculate distance between two points on Earth
Home-page: https://github.com/reisgoldmanX/dist_calculations
Author: reisgoldmanX (U D)
Author-email: <reisgoldman@gmail.com>
License: UNKNOWN
Keywords: python,geography,meridian,distance calculations,earth,parallel
Platform: UNKNOWN
Classifier: Programming Language :: Python :: 3
Classifier: Intended Audience :: Developers
Classifier: License :: OSI Approved :: MIT License
Classifier: Operating System :: Unix
Classifier: Operating System :: MacOS :: MacOS X
Classifier: Operating System :: Microsoft :: Windows
License-File: LICENSE
